<?xml version="1.0" encoding="BIG5"?>
<CMBSDKPGK>
	<INFO>
		<FUNNAM>GetNewNotice</FUNNAM>
		<DATTYP>2</DATTYP>
		<RETCOD>0</RETCOD>
		<ERRMSG></ERRMSG>
	</INFO>
	<NTQNTCGTZ>
		<MSGTYP>NCCRTTRS</MSGTYP>
		<MSGNBR>200609280001298930</MSGNBR>
		<TRSDAT>20080507</TRSDAT>
		<TRSTIM>000000</TRSTIM>
		<FLWTYP></FLWTYP>
		<REQDTA></REQDTA>
		<BBKNBR>91</BBKNBR>
		<ACCNBR>3180085810001</ACCNBR>
		<CCYNBR>10</CCYNBR>
		<YURREF>APP060915000150</YURREF>
		<ACCNAM>北京集團公司深圳分公司</ACCNAM>
		<TRSAMT>1.01</TRSAMT>
		<EPTDAT>20060928</EPTDAT>
		<EPTTIM>000000</EPTTIM>
		<OPRDAT>20060928</OPRDAT>
		<RTNFLG>F</RTNFLG>
		<RTNDSP>NCB4241業務參考號重復</RTNDSP>
	</NTQNTCGTZ>
	<NTQNTCGTZ>
		<MSGTYP>NCCRTTRS</MSGTYP>
		<MSGNBR>200609280001298931</MSGNBR>
		<TRSDAT>20080507</TRSDAT>
		<TRSTIM>000000</TRSTIM>
		<BBKNBR>91</BBKNBR>
		<ACCNBR>3180085810001</ACCNBR>
		<CCYNBR>10</CCYNBR>
		<TRSAMT>1.01</TRSAMT>
		<BLVAMT>268.00</BLVAMT>
		<ACCNAM>北京集團公司深圳分公司</ACCNAM>
		<EPTDAT>20060928</EPTDAT>
		<EPTTIM>000000</EPTTIM>
		<AMTCDR>C</AMTCDR>
		<RVSTAG></RVSTAG>
		<VALDAT></VALDAT>
		<BILTYP></BILTYP>
		<BILTXT></BILTXT>
		<BILNBR></BILNBR>
		<TRSSET></TRSSET>
		<SEQNBR></SEQNBR>
		<NARTXT></NARTXT>
		<RPYBBK></RPYBBK>
		<RPYACC>1280078810099</RPYACC>
		<RPYNAM>北京集團公司收方帳號</RPYNAM>
		<RPYBBN></RPYBBN>
		<RPYBNK>招商銀行烏魯木齊分行</RPYBNK>
		<RPYADR>新疆維吾爾自治區烏魯木齊市</RPYADR>
		<GSBBBK></GSBBBK>
		<GSBACC></GSBACC>
		<GSBNAM></GSBNAM>
		<GSBBBN></GSBBBN>
		<GSBBNK></GSBBNK>
		<GSBADR></GSBADR>
		<INFFLG>1</INFFLG>
		<TRSANL></TRSANL>
		<YURREF></YURREF>
		<BUSNAR></BUSNAR>
	</NTQNTCGTZ>
</CMBSDKPGK>
